backupp/Backup_base.py
backupp/Backup_src.py
backupp/Directory.py
backupp/__init__.py
backupp/_options.py
backupp/backup_with_path.py
backupp/colors.py
backupp/copy_ops.py
backupp/display.py
backupp/file_checks.py
backupp/file_classes.py
backupp/files.py
backupp/github_actions.py
backupp/main_funcs_to_load.py
backupp/menu.py
backupp/onload_parser.py
backupp/options.cfg
backupp/py_template.py
backupp/read_ignore.py
backupp/read_ignore_helpers.py
backupp/read_ignore_templates.py
backupp/template_on_load.py
backupp/tests/__init__.py
backupp/tests/test_console_actions_.py
backupp/tests/test_ignore.py
backupp/tests/tests_main.py
backupp/type_defs.py
backupp/utils.py
backupp-0.0.19.dist-info/LICENSE
backupp-0.0.19.dist-info/METADATA
backupp-0.0.19.dist-info/WHEEL
backupp-0.0.19.dist-info/entry_points.txt
backupp-0.0.19.dist-info/RECORD
