Metadata-Version: 2.1
Name: backupp
Version: 0.0.19
Summary: Back ups your folder to your preferred local or network destination reading or creating a gitignore file.
License: MIT
Author: Sermet Pekin
Author-email: sermet.pekin@gmail.com
Requires-Python: >=3.9,<4.0
Classifier: License :: OSI Approved :: MIT License
Classifier: Programming Language :: Python :: 3
Classifier: Programming Language :: Python :: 3.9
Classifier: Programming Language :: Python :: 3.10
Classifier: Programming Language :: Python :: 3.11
Classifier: Programming Language :: Python :: 3.12
Requires-Dist: gitignore-parser (>=0.1.11,<0.2.0)
Requires-Dist: rich (>=13.7.1,<14.0.0)
